<annotation verified="yes">
    <folder>Annotation</folder>
    <filename>dog.3363.jpg</filename>
    <path>Dog-PascalVOC-export/Annotations/dog.3363.jpg</path>
    <source>
        <database>Unknown</database>
    </source>
    <size>
        <width>256</width>
        <height>256</height>
        <depth>3</depth>
    </size>
    <segmented>0</segmented>
    <object>
    <name>dog</name>
    <pose>Unspecified</pose>
    <truncated>0</truncated>
    <difficult>0</difficult>
    <bndbox>
        <xmin>30.770623675847457</xmin>
        <ymin>12.727685271009888</ymin>
        <xmax>237.88475459039546</xmax>
        <ymax>213.47797492937852</ymax>
    </bndbox>
</object>
</annotation>
