<annotation verified="yes">
    <folder>Annotation</folder>
    <filename>dog.8830.jpg</filename>
    <path>dog_new-PascalVOC-export/Annotations/dog.8830.jpg</path>
    <source>
        <database>Unknown</database>
    </source>
    <size>
        <width>256</width>
        <height>256</height>
        <depth>3</depth>
    </size>
    <segmented>0</segmented>
    <object>
    <name>dog</name>
    <pose>Unspecified</pose>
    <truncated>0</truncated>
    <difficult>0</difficult>
    <bndbox>
        <xmin>2.422603283898305</xmin>
        <ymin>35.579664327330505</ymin>
        <xmax>240.090395480226</xmax>
        <ymax>254.2644111935028</ymax>
    </bndbox>
</object>
</annotation>
