<annotation verified="yes">
    <folder>Annotation</folder>
    <filename>dog.3431.jpg</filename>
    <path>Dog-PascalVOC-export/Annotations/dog.3431.jpg</path>
    <source>
        <database>Unknown</database>
    </source>
    <size>
        <width>256</width>
        <height>256</height>
        <depth>3</depth>
    </size>
    <segmented>0</segmented>
    <object>
    <name>dog</name>
    <pose>Unspecified</pose>
    <truncated>0</truncated>
    <difficult>0</difficult>
    <bndbox>
        <xmin>37.7130009710452</xmin>
        <ymin>49.46440788312147</ymin>
        <xmax>226.60341631355934</xmax>
        <ymax>252.2395612641243</ymax>
    </bndbox>
</object>
</annotation>
